xmlplain.py
xmlplain-1.6.0.dist-info/METADATA
xmlplain-1.6.0.dist-info/RECORD
xmlplain-1.6.0.dist-info/WHEEL
xmlplain-1.6.0.dist-info/top_level.txt
xmlplain-1.6.0.dist-info/zip-safe
