Metadata-Version: 2.1
Name: xmlplain
Version: 1.6.0
Summary: XML as plain object module
Home-page: https://github.com/guillon/xmlplain
Author: Christophe Guillon
Author-email: christophe.guillon.perso@gmail.com
License: unlicense
Platform: UNKNOWN
Classifier: Development Status :: 5 - Production/Stable
Classifier: Environment :: Console
Classifier: Intended Audience :: Developers
Classifier: License :: Public Domain
Classifier: Operating System :: POSIX :: Linux
Classifier: Programming Language :: Python :: 2.6
Classifier: Programming Language :: Python :: 2.7
Classifier: Programming Language :: Python :: 3.4
Classifier: Programming Language :: Python :: 3.5
Classifier: Programming Language :: Python :: 3.6
Classifier: Topic :: Text Processing :: Markup :: XML
